desbordante-stubs/__init__.pyi
desbordante-stubs/ac/__init__.pyi
desbordante-stubs/ac/algorithms.pyi
desbordante-stubs/afd/__init__.pyi
desbordante-stubs/afd/algorithms.pyi
desbordante-stubs/aind/__init__.pyi
desbordante-stubs/aind/algorithms.pyi
desbordante-stubs/ar/__init__.pyi
desbordante-stubs/ar/algorithms.pyi
desbordante-stubs/cfd/__init__.pyi
desbordante-stubs/cfd/algorithms.pyi
desbordante-stubs/data_types.pyi
desbordante-stubs/dc/__init__.pyi
desbordante-stubs/dc/algorithms.pyi
desbordante-stubs/dc_verification/__init__.pyi
desbordante-stubs/dc_verification/algorithms.pyi
desbordante-stubs/dd/__init__.pyi
desbordante-stubs/dd/algorithms.pyi
desbordante-stubs/dynamic_fd_verification/__init__.pyi
desbordante-stubs/dynamic_fd_verification/algorithms.pyi
desbordante-stubs/fd/__init__.pyi
desbordante-stubs/fd/algorithms.pyi
desbordante-stubs/fd_verification/__init__.pyi
desbordante-stubs/fd_verification/algorithms.pyi
desbordante-stubs/gfd_verification/__init__.pyi
desbordante-stubs/gfd_verification/algorithms.pyi
desbordante-stubs/ind/__init__.pyi
desbordante-stubs/ind/algorithms.pyi
desbordante-stubs/ind_verification/__init__.pyi
desbordante-stubs/ind_verification/algorithms.pyi
desbordante-stubs/md/__init__.pyi
desbordante-stubs/md/algorithms.pyi
desbordante-stubs/md/column_matches.pyi
desbordante-stubs/mfd_verification/__init__.pyi
desbordante-stubs/mfd_verification/algorithms.pyi
desbordante-stubs/nar/__init__.pyi
desbordante-stubs/nar/algorithms.pyi
desbordante-stubs/nd.pyi
desbordante-stubs/nd_verification/__init__.pyi
desbordante-stubs/nd_verification/algorithms.pyi
desbordante-stubs/od/__init__.pyi
desbordante-stubs/od/algorithms.pyi
desbordante-stubs/pfd/__init__.pyi
desbordante-stubs/pfd/algorithms.pyi
desbordante-stubs/pfd_verification/__init__.pyi
desbordante-stubs/pfd_verification/algorithms.pyi
desbordante-stubs/relational_schema.pyi
desbordante-stubs/sfd/__init__.pyi
desbordante-stubs/sfd/algorithms.pyi
desbordante-stubs/statistics/__init__.pyi
desbordante_stubs-0.3.0.dist-info/METADATA
desbordante_stubs-0.3.0.dist-info/WHEEL
desbordante_stubs-0.3.0.dist-info/RECORD
