Metadata-Version: 2.1
Name: desbordante-stubs
Version: 0.3.0
Summary: Stubs for desbordante package
License: BSD-3-Clause
Author: Vadim Yakshigulov
Author-email: toadharvard@gmail.com
Requires-Python: >=3.11,<4.0
Classifier: License :: OSI Approved :: BSD License
Classifier: Programming Language :: Python :: 3
Classifier: Programming Language :: Python :: 3.11
Classifier: Programming Language :: Python :: 3.12
Requires-Dist: desbordante (>=2.3.2,<3.0.0)
